{
  "E08": {
    "status": 0,
    "signal": "Tankers (FRO/STNG/DHT) moy vs MA20 : -1.7%",
    "reasoning": "FRO: -3.2% | STNG: +1.3% | DHT: -3.2%",
    "source": "yFinance",
    "updated_at": "2026-07-14T06:17:45.118876"
  },
  "E09": {
    "status": 0,
    "signal": "Brent 84.8$/bbl vs MA30 82.2$ → +3.1%",
    "reasoning": "Déviation de +3.1% par rapport à la moyenne 30j. Seuils : Veille +8%, Alerte +15%, Déclenché +25%.",
    "source": "yFinance",
    "updated_at": "2026-07-14T06:17:45.118876"
  }
}